scientimate/__init__.py
scientimate/colormap/__init__.py
scientimate/colormap/gencolormap.py
scientimate/colormap/seqcolormap.py
scientimate/colormap/topocolormap.py
scientimate/data_downloading/__init__.py
scientimate/data_downloading/downloadndbcdata.py
scientimate/data_downloading/downloadtidecurrentdata.py
scientimate/data_manipulating/__init__.py
scientimate/data_manipulating/downsamplex.py
scientimate/data_manipulating/downsamplexy.py
scientimate/data_manipulating/downsamplexyz.py
scientimate/data_manipulating/interpgrid2xyz.py
scientimate/data_manipulating/interpxyz2grid.py
scientimate/data_manipulating/interpxyz2xyz.py
scientimate/data_manipulating/replacemissing1d.py
scientimate/data_manipulating/replacemissing2d.py
scientimate/data_manipulating/replaceoutlier.py
scientimate/data_manipulating/replacespike3dps.py
scientimate/data_manipulating/replacespikediff.py
scientimate/data_manipulating/replacespikeenvelope.py
scientimate/data_reading/__init__.py
scientimate/data_reading/readasciitable.py
scientimate/data_reading/readdatafile.py
scientimate/data_reading/readtimeseriestable.py
scientimate/data_reading/readxyzfile.py
scientimate/hurricane/__init__.py
scientimate/hurricane/hurricanebackgroundwind.py
scientimate/hurricane/hurricanedpcpt.py
scientimate/hurricane/hurricanepressureh80.py
scientimate/hurricane/hurricanetranslationvel.py
scientimate/hurricane/hurricanewavecontourcem.py
scientimate/hurricane/hurricanewavecontourh16.py
scientimate/hurricane/hurricanewavecontoury88.py
scientimate/hurricane/hurricanewavemax.py
scientimate/hurricane/hurricanewindh08.py
scientimate/hurricane/hurricanewindh80.py
scientimate/hurricane/hurricanewindinflowangle.py
scientimate/hurricane/hurricanewindvel.py
scientimate/hurricane/hurricanewindvelmax.py
scientimate/hurricane/hurricanewindvelmaxh08.py
scientimate/hurricane/hurricanewindvelmaxh80.py
scientimate/hurricane/readnhchurricane.py
scientimate/hurricane/stormsurge1d.py
scientimate/mapping/__init__.py
scientimate-2.0.dist-info/License.txt
scientimate-2.0.dist-info/METADATA
scientimate-2.0.dist-info/WHEEL
scientimate-2.0.dist-info/top_level.txt
scientimate-2.0.dist-info/RECORD
