Metadata-Version: 2.1
Name: scientimate
Version: 2.0
Summary: Coastal and Ocean Data Analysis Library
Home-page: https://github.com/akarimp/ScientiMate
Author: Arash Karimpour
Author-email: arkarimp@gmail.com
Classifier: Programming Language :: Python :: 3
Classifier: License :: OSI Approved :: MIT License
Classifier: Operating System :: OS Independent
Requires-Python: >=3.6
License-File: License.txt
Requires-Dist: numpy
Requires-Dist: scipy
Requires-Dist: pandas
Requires-Dist: matplotlib
